{"type":"article","id":1851,"title":"断梯子的解决方案","uid":5359,"topics":[],"contents":"从各路朋友了解到，昨天开始，各地都开始出现了SS或者SSR类似的梯子被砍断的情况。<br>\n<br>\n今天在家找了很久的原因，总算有些发现，也意味着有了解决方案了。<br>\n<br>\n主要有两种情况，一是IP被封，这个司空见惯，想办法更换个IP就是。<br>\n<br>\n第二种是我还没见过的，IP不封，但这个IP的特定端口给你封掉，22，3389之类的你建了VPS也无法远程连接上去。或者是我自己的VPS上，其他web服务还工作的好好的，唯独SS的端口被封掉了。<br>\n<br>\n方法1：换IP，大家都会但是可能很快又被被墙<br>\n方法2：把SS的端口调整到其他还能使用的端口上去，这也只是个临时对策，说不定哪天又被墙了<br>\n方法3：走IPV6，目前IPV6的梯子还不高，直接使用支持IPV6的服务器，SS服务走IPV6访问，彻底告别IPV4的梯子，谷歌目前不支持IPV6还是比较可惜，其他家的速度又比不过，不过特殊时期但愿后面能重新放开一点。","date":"2019-06-02","agreeCount":1,"discussionCount":0}