{"type":"article","id":5904,"title":"中国的网络评论环境为什么恶劣到了这种几乎可以说是无死角且不可救药的地步？","uid":3480,"topics":[],"contents":"对于国内网络上评论可能带给人的精神污染，我平时可以说是非常谨慎提防了！不仅涉政内容我从不看评论，就连看视频也基本不开弹幕。但我真是没想到就连网易云上一首大概是抒发寂寞之情的日语歌下的评论，竟然也能被带到这种粉红的气氛中：<br>\n<blockquote>各位，日本没有天堂，没有动漫中的唯美和撕心裂肺，一个人的日本，每天只有20平米的房子，只有在电车里无神望着窗外，只有排外严重的日本人，只有绝美的景色却没人陪你看，日本啊，真像动漫里的日本就好了</blockquote><br>\n<blockquote>在日本有排外的也有亲切的。我去大阪的时候有自以为我们听不懂日语的说我们坏话。意思大概就是中国人很麻烦啊之类的。当时真的很想抽他。但是也有一个大叔带我去高岛屋走了半个小时的。还有看到我没有手套主动握住我的手帮我取暖的老板娘。每个国家都有各种各样的人。</blockquote><br>\n<blockquote>不是像极了动漫里的日本吗？正是这样压抑孤独的生活，才会催生那么多想去炸裂世界的故事，那么多只能依赖动漫世界来撕裂声带的呐喊，动漫里最写实的是坐电车一个人，静静心碎的时刻</blockquote><br>\n第1条留言自不必说，第2第3条虽不算太粉红，但回复这样和歌曲八杆子打不着的留言还这样心平气和，也让我感到奇怪。<br>\n但最奇怪的一点就在于这第1条留言居然是点赞最高的留言，15万多的点赞数……<br>\n这种情况能不能说明这样一个事实，即在中文网络上，已经很难找到一个单纯讨论事物本身，而不牵涉任何排外及民族主义的环境了呢？<br>\n各位有没有遇到过像我这样的情况，即被这种和要讨论的事物并无关系的留言给恶心到？<br>\n<br>\n<br>\n<br>\n当然我承认任何国家都有网络喷子，比如我听说某台湾画师因在推上发表1乳摇色情图被一些日本网民围喷质疑其对日本震灾幸灾乐祸……<br>\n但我还是认为在一个信息开放自由的网络环境，喷子是个人行为和情况不足为虑。<br>\n但中国这种信息被严格控制的网络环境，煞笔被五毛像各位葱友所说这样批量引导出来才叫可怕","date":"2019-10-03","agreeCount":5,"discussionCount":0}