{"type":"article","id":9188,"title":"[经略新闻集萃]  之 &lt;90&gt; 反送中运动下的选举 香港人能否用选票“光复香港”？","uid":798,"topics":[847],"contents":"经略楼, 4832时政评论<br>\n<br>\n<br>\n<a href=\"https://www.reddit.com/r/4832/comments/dzzny3/%E6%88%98%E4%BA%89%E4%BF%A1%E5%8F%B7%E4%B8%AD%E5%9B%BD%E5%A4%96%E4%BA%A4%E9%83%A8%E7%8B%82%E8%BD%B0%E9%A6%99%E6%B8%AF%E6%B3%95%E6%A1%88_%E5%8F%91%E5%87%BA%E7%BD%95%E8%A7%81%E6%8E%AA%E8%AF%8D%E8%AD%A6%E5%91%8A/\" rel=\"nofollow noreferrer noopener\" target=\"_blank\">战争信号？中国外交部狂轰香港法案 发出「罕见措词」警告</a><br>\n<br>\n<br>\n<a href=\"https://www.reddit.com/r/4832/comments/dzzmrw/%E9%83%91%E6%96%87%E6%9D%B0%E6%83%8A%E7%88%86%E5%86%85%E5%B9%95%E5%A4%A7%E6%89%B9%E9%A6%99%E6%B8%AF%E6%8A%97%E4%BA%89%E8%80%85%E8%A2%AB%E9%80%81%E4%B8%AD%E5%A3%B0%E6%98%8E%E4%B8%AD%E8%AF%91%E5%85%A8%E6%96%87/\" rel=\"nofollow noreferrer noopener\" target=\"_blank\">郑文杰惊爆内幕：大批香港抗争者被送中（声明中译全文）</a><br>\n<br>\n<br>\n<a href=\"https://www.reddit.com/r/4832/comments/dzzkrc/%E5%8C%97%E4%BA%AC%E7%A7%80%E9%83%91%E6%96%87%E6%9D%B0%E5%AB%96%E5%A8%BC%E7%96%91%E7%82%B9%E9%87%8D%E9%87%8D/\" rel=\"nofollow noreferrer noopener\" target=\"_blank\">北京秀郑文杰嫖娼疑点重重</a><br>\n<br>\n<br>\n<a href=\"https://www.reddit.com/r/4832/comments/dzzjrp/%E6%9F%8F%E6%9E%97%E5%B7%A5%E4%B8%9A%E5%A4%A7%E5%AD%A6%E5%AD%A6%E7%94%9F%E4%BC%9A%E5%8A%9B%E6%8C%BA%E9%A6%99%E6%B8%AF%E7%90%86%E5%A4%A7%E7%A4%BA%E5%A8%81%E8%80%85_%E4%B8%AD%E5%9B%BD%E7%95%99%E5%AD%A6%E7%94%9F%E7%BB%84%E7%BB%87%E5%9B%B4%E6%94%BB/\" rel=\"nofollow noreferrer noopener\" target=\"_blank\">柏林工业大学学生会力挺香港理大示威者 中国留学生组织围攻</a><br>\n<br>\n<br>\n<a href=\"https://www.reddit.com/r/4832/comments/dzzj5h/%E7%BE%8E%E5%9B%BD%E7%AD%89%E5%88%B0%E4%BA%86%E8%BF%99%E5%BC%A0%E7%89%8C/\" rel=\"nofollow noreferrer noopener\" target=\"_blank\">美国等到了这张牌</a><br>\n<br>\n<br>\n<a href=\"https://www.reddit.com/r/4832/comments/e00fad/%E8%B0%81%E6%98%AF%E6%96%B0%E7%96%86%E7%BB%9D%E5%AF%86%E6%96%87%E4%BB%B6%E7%9A%84%E6%B3%84%E5%AF%86%E8%80%85%E8%B0%81%E6%98%AF%E4%B8%AD%E5%9B%BD%E5%BD%93%E4%BB%A3%E7%9A%84%E8%BE%9B%E5%BE%B7%E5%8B%92/\" rel=\"nofollow noreferrer noopener\" target=\"_blank\">谁是新疆绝密文件的泄密者？谁是中国当代的辛德勒？</a><br>\n<br>\n<br>\n<a href=\"https://www.reddit.com/r/4832/comments/e00dla/%E4%B8%80%E4%B8%AA%E9%A6%99%E6%B8%AF%E5%A5%B3%E5%AD%A9%E4%BB%A4%E4%BA%BA%E8%82%9D%E8%82%A0%E5%AF%B8%E6%96%AD%E7%9A%84%E8%AF%97/\" rel=\"nofollow noreferrer noopener\" target=\"_blank\">一个香港女孩令人肝肠寸断的诗</a><br>\n<br>\n<br>\n<a href=\"https://www.reddit.com/r/4832/comments/e0019f/%E6%B7%B1%E5%9C%B3%E6%B9%BE%E4%BD%93%E8%82%B2%E4%B8%AD%E5%BF%83%E9%9B%86%E7%BB%93%E5%A4%A7%E6%89%B9%E5%86%9B%E8%BD%A6%E6%AD%A6%E8%AD%A6%E6%88%96%E9%95%BF%E9%A9%BB/\" rel=\"nofollow noreferrer noopener\" target=\"_blank\">深圳湾体育中心集结大批军车武警或长驻</a><br>\n<br>\n<br>\n<a href=\"https://www.reddit.com/r/4832/comments/dzzuna/%E9%99%88%E5%98%89%E5%AE%8F%E4%B8%93%E6%A0%8F%E9%9F%A9%E5%9B%BD%E7%91%9C%E4%BB%A5%E4%B8%BA%E8%87%AA%E5%B7%B1%E5%9C%A8%E9%80%89%E9%87%8C%E9%95%BF%E5%90%97/\" rel=\"nofollow noreferrer noopener\" target=\"_blank\">陈嘉宏专栏：韩国瑜以为自己在选里长吗</a><br>\n<br>\n<br>\n<a href=\"https://www.reddit.com/r/4832/comments/dzzgq8/%E5%B8%83%E9%9A%86%E4%BC%AF%E6%A0%BC%E9%80%92%E4%BA%A4%E6%96%87%E4%BB%B6%E5%8F%82%E9%80%89%E7%BE%8E%E5%9B%BD%E6%80%BB%E7%BB%9F/\" rel=\"nofollow noreferrer noopener\" target=\"_blank\">布隆伯格递交文件参选美国总统</a><br>\n<br>\n<br>\n<a href=\"https://www.reddit.com/r/4832/comments/dzzesw/%E7%BE%8E%E4%B8%A4%E5%85%9A%E5%8F%82%E8%AE%AE%E5%91%98%E5%8F%8D%E5%AF%B9%E5%95%86%E5%8A%A1%E9%83%A8%E5%87%86%E8%AE%B8%E9%83%A8%E5%88%86%E7%BE%8E%E5%9B%BD%E5%85%AC%E5%8F%B8%E5%90%91%E5%8D%8E%E4%B8%BA%E4%BE%9B%E8%B4%A7/\" rel=\"nofollow noreferrer noopener\" target=\"_blank\">美两党参议员反对商务部准许部分美国公司向华为供货</a><br>\n<br>\n<br>\n<a href=\"https://www.reddit.com/r/4832/comments/dzzdek/%E7%90%86%E5%A4%A7%E6%9C%80%E6%96%B0%E6%83%85%E5%86%B5%E7%BA%A650%E4%BA%BA%E7%95%99%E5%AE%88_%E5%85%B6%E4%B8%AD10%E5%90%8D%E6%9C%AA%E6%88%90%E5%B9%B4/\" rel=\"nofollow noreferrer noopener\" target=\"_blank\">理大最新情况：约50人留守 其中10名未成年</a><br>\n<br>\n<br>\n<a href=\"https://www.reddit.com/r/4832/comments/dzzcl1/%E7%BE%8E%E8%B5%84%E6%B7%B1%E5%8F%82%E8%AE%AE%E5%91%98%E4%B8%AD%E5%85%B1%E5%BA%94%E5%81%9C%E6%AD%A2%E5%B9%B2%E9%A2%84%E7%BE%8E%E5%9B%BD%E5%86%85%E6%94%BF/\" rel=\"nofollow noreferrer noopener\" target=\"_blank\">美资深参议员：中共应停止干预美国内政</a><br>\n<br>\n<br>\n<a href=\"https://www.reddit.com/r/4832/comments/dzzb7m/%E8%8D%B7%E5%AA%92%E8%AE%BF%E6%B8%AF%E7%A4%BA%E5%A8%81%E9%9D%92%E5%B9%B4_%E5%BF%A7%E5%8C%97%E4%BA%AC%E5%B9%B2%E9%A2%84%E6%B6%88%E7%81%AD%E4%B8%80%E6%95%B4%E4%B8%AA%E4%B8%96%E4%BB%A3/\" rel=\"nofollow noreferrer noopener\" target=\"_blank\">荷媒访港示威青年 忧北京干预消灭一整个世代</a><br>\n<br>\n<br>\n<a href=\"https://www.reddit.com/r/4832/comments/dzz9sz/%E5%90%83%E9%A5%AD%E5%95%B0%E7%90%86%E5%A4%A7%E6%8A%97%E4%BA%89%E4%B8%AD%E7%9A%84%E6%88%98%E6%96%97%E6%97%A5%E5%B8%B8/\" rel=\"nofollow noreferrer noopener\" target=\"_blank\">「吃饭啰！」理大抗争中的战斗日常</a><br>\n<br>\n<br>\n<a href=\"https://www.reddit.com/r/4832/comments/dzz94m/%E7%BE%8E%E6%96%BD%E5%8E%8B%E5%A5%8F%E6%95%88_%E5%8D%97%E9%9F%A9%E5%86%B3%E5%AE%9A%E7%BB%A7%E7%BB%AD%E7%BB%B4%E6%8C%81%E9%9F%A9%E6%97%A5%E5%86%9B%E6%83%85%E5%8D%8F%E5%AE%9A/\" rel=\"nofollow noreferrer noopener\" target=\"_blank\">美施压奏效 南韩决定继续维持韩日军情协定</a><br>\n<br>\n<br>\n<a href=\"https://www.reddit.com/r/4832/comments/dzz8hx/%E4%B8%AD%E5%9B%BD%E5%9C%A8%E9%9F%A9%E5%9B%BD%E7%95%99%E5%AD%A6%E7%94%9F%E5%9C%A8%E5%BE%AE%E5%8D%9A%E6%9A%B4%E5%8A%9B%E5%A8%81%E8%83%81%E9%9F%A9%E5%9B%BD%E6%94%AF%E6%8C%81%E9%A6%99%E6%B8%AF%E7%9A%84%E5%A4%A7%E5%AD%A6%E7%94%9F/\" rel=\"nofollow noreferrer noopener\" target=\"_blank\">中国在韩国留学生在微博暴力威胁韩国支持香港的大学生</a><br>\n<br>\n<br>\n<a href=\"https://www.reddit.com/r/4832/comments/dzz7mf/%E5%B8%83%E9%B2%81%E5%85%8B%E6%96%AF%E4%BB%8A%E5%90%8E%E5%87%A0%E5%91%A8%E5%B0%86%E5%86%B3%E5%AE%9A%E9%9F%A9%E7%BE%8E%E5%90%8C%E7%9B%9F%E7%9A%84%E6%9C%AA%E6%9D%A5/\" rel=\"nofollow noreferrer noopener\" target=\"_blank\">布鲁克斯：今后几周将决定韩美同盟的未来</a><br>\n<br>\n<br>\n<a href=\"https://www.reddit.com/r/4832/comments/dzttct/%E4%B8%AD%E5%9B%BD%E9%87%91%E6%8F%B4%E5%A4%96%E4%BA%A4%E7%88%86%E4%B8%91%E9%97%BB_%E4%BA%BF%E4%B8%89%E7%BE%8E%E5%85%83%E6%8F%B4%E5%8A%A9%E6%B4%A5%E5%B7%B4%E5%B8%83%E9%9F%A6%E5%8F%98%E4%B8%89%E7%99%BE%E5%85%AD%E5%8D%81%E4%B8%87/\" rel=\"nofollow noreferrer noopener\" target=\"_blank\">中国金援外交爆丑闻 亿三美元援助津巴布韦变三百六十万</a><br>\n<br>\n<br>\n<a href=\"https://www.reddit.com/r/4832/comments/dzuf1e/spacex%E6%98%9F%E9%99%85%E9%A3%9E%E8%88%B9%E6%B5%8B%E8%AF%95%E4%B8%AD%E5%8F%91%E7%94%9F%E7%88%86%E8%A3%82_%E7%A1%AC%E4%BB%B6%E5%9B%9B%E5%A4%84%E9%A3%9E%E5%B0%84/\" rel=\"nofollow noreferrer noopener\" target=\"_blank\">SpaceX星际飞船测试中发生爆裂 硬件四处飞射</a><br>\n<br>\n<br>\n<a href=\"https://www.reddit.com/r/4832/comments/dzu1q0/%E8%BF%99%E5%A8%98%E4%BB%AC%E4%B9%9F%E5%8F%AF%E4%BB%A5%E5%8D%95%E7%8B%AC%E5%87%BA%E6%9D%A5%E4%BC%9A%E8%A7%81%E6%AF%94%E5%B0%94%E7%9B%96%E8%8C%A8%E5%9B%BE/\" rel=\"nofollow noreferrer noopener\" target=\"_blank\">这娘们也可以单独出来会见比尔.盖茨（图）</a><br>\n<br>\n<br>\n<a href=\"https://www.reddit.com/r/4832/comments/dztqbf/%E6%B4%9B%E6%A1%91%E6%A3%AE%E6%A0%BC%E9%95%87%E5%8E%8B%E8%A5%BF%E8%97%8F%E6%96%B9%E6%B3%95%E6%AD%A3%E5%9C%A8%E4%B8%AD%E5%9B%BD%E6%89%A9%E6%95%A3/\" rel=\"nofollow noreferrer noopener\" target=\"_blank\">洛桑森格：镇压西藏方法正在中国扩散</a><br>\n<br>\n<br>\n<a href=\"https://www.reddit.com/r/4832/comments/dzto6s/%E8%B4%B8%E6%98%93%E8%B0%88%E5%88%A4%E5%88%98%E9%B9%A4%E7%A2%B0%E8%BD%AF%E9%92%89%E5%AD%90_%E4%B8%AD%E5%9B%BD%E5%88%B6%E9%80%A0202520%E7%89%88%E6%A8%AA%E7%A9%BA%E5%87%BA%E4%B8%96/\" rel=\"nofollow noreferrer noopener\" target=\"_blank\">贸易谈判刘鹤碰软钉子 “中国制造2025”2.0版横空出世</a><br>\n<br>\n<br>\n<a href=\"https://www.reddit.com/r/4832/comments/dztn02/%E5%8F%8D%E9%80%81%E4%B8%AD%E8%BF%90%E5%8A%A8%E4%B8%8B%E7%9A%84%E9%80%89%E4%B8%BE_%E9%A6%99%E6%B8%AF%E4%BA%BA%E8%83%BD%E5%90%A6%E7%94%A8%E9%80%89%E7%A5%A8%E5%85%89%E5%A4%8D%E9%A6%99%E6%B8%AF/\" rel=\"nofollow noreferrer noopener\" target=\"_blank\">反送中运动下的选举 香港人能否用选票“光复香港”？</a><br>\n<br>\n<br>\n<a href=\"https://www.reddit.com/r/4832/comments/dztlko/%E4%B8%A4%E9%A1%B9%E6%B6%89%E6%B8%AF%E6%B3%95%E6%A1%88%E9%80%9A%E8%BF%87_%E5%AF%B9%E9%A6%99%E6%B8%AF%E6%84%8F%E5%91%B3%E7%9D%80%E4%BB%80%E4%B9%88/\" rel=\"nofollow noreferrer noopener\" target=\"_blank\">两项涉港法案通过 对香港意味着什么</a><br>\n<br>\n<br>\nRSS feed: https://www.reddit.com/r/4832.rss","date":"2019-11-22","agreeCount":0,"discussionCount":0}