{"type":"answer_discussion","id":323912,"uid":30064,"date":"2020-07-20","contents":"@pincong360:对于达到条件的人，本来就是十分简单。。。入籍。<br>\n这个在哪个国家都一样。。<br>\n日本是制造业强国 也是大国。。再加上老龄化，工作机会是非常的多。 要找个稳定的工作还是很简单的。<br>\n<br>\n那些说 澳洲，新西兰，英国，美国啥的 入籍难的是因为非常难找工作啊。。。<br>\n连个像样的工作都找不到的人 肯定没法入籍了。<br>\n你要是找个Google 或者 apple Amazon 这样的公司的 正式职员的工作。。也是非常入籍的。。啊。。。<br>\n<br>\n我倒是去过不少发达国家了。还是觉得日本最好。<br>\n最干净。整洁 。 人的素质最高。。治安最好。<br>\n<br>\n估计除了北欧三国 加新西兰 没有比日本适合生活的地方了。。<br>\n夏威夷也不错。 财富自由的话每年 去度假3个月。。","parentType":"answer","parentId":307678}