{"type":"answer","id":340118,"parentType":"question","parentId":30951,"uid":23171,"contents":"簡單說，王金平應該還是會去<br>\n國民黨呢？不知道，看這個海峽論壇背後是中共的誰<br>\n大家都知道中共內部也有派系，也會互鬥，但講到一些議題的時候感覺都有把中共當鐵板一塊的傾向<br>\n這次央視會出來說王金平是去求和，我想就是中共內部不同系統衝突的結果<br>\n讓央視講出求和的那一派顯然跟黃復興比較好<br>\n<br>\n王金平本人是很有野心的<br>\n去年年初的時候他為了爭取國民黨提名也跟著做直播上夜夜秀之類的，做了很多不符合他形象的事<br>\n結果被韓國瑜這廢物搞得亂七八糟，所有努力付諸流水，我想他肯定很不甘心<br>\n而這次對他來說是個機會<br>\n他去海峽論壇也不需要舔，甚至有機會上電視的話還可以學陳菊來句中華民國<br>\n反正只要講得含蓄一點中共八成也不會對他怎樣，頂多把他受訪的片段剪掉然後叫囂幾句甚麼的<br>\n但這一但在台灣媒體上曝光，他立刻就變成最有GUTS的國民黨黨員<br>\n柯文哲垂涎了好幾年的淺藍票直接就是他的，甚至可以收穫一些淺綠<br>\n到時候就算黃復興不支持他，他也可以藉這個機會拉攏朱立倫侯友宜和一些地方勢力壓倒黃復興<br>\n對王金平來說反正狀況也不會比現在更差了，幹嘛不試試看？<br>\n<br>\n當然，前提是他敢講<br>\n他不敢的話去了也是白去，還不如回家睡覺","date":"2020-09-15","agreeCount":0,"discussionCount":0}