{"type":"article_comment","id":96098,"parentType":"article","parentId":7212,"uid":728,"contents":"这篇文章最大的价值不在于他批判孙或者辛怎么样，而在于他讲清楚“<b>民主社会和专制社会是不一样的。如果他们想让中国有朝一日获得民主，他们首先需要的，不是闭门造车，而是真的出来，看看民主社会是什么样的。”</b>芝士份子长期和社会大众脱节，根本不知道怎么去发动群众，讲来讲去其实听自己讲话的绝大多数都是和自己一样的芝士份子。这是他们根本无法成功的原因所在。当然姨粉基本上也是知识分子出身，在大洪水之前并不比民运更强，也因此遭到了大一统芝士份子们的嘲讽，但这些大一统芝士份子向来是只看到别人眼里的刺，看不到自己眼中的梁木的。<br>\n所以他说孙对辛亥革命没什么价值我就深以为然。孙和武昌前线官兵的隔阂太大了，所能施加的影响只会比丁玲或者萧红对延安老农民的影响更小（后者至少身在现场呢）。共产党用血仇来挑拨农民和乡绅关系（这一点原文讲的很清楚，我就不费口舌了）才发动了农民们对其效忠，但这种黑手他没法承认，所以才把发动农民的功劳算到那些芝士份子头上，顺便还能把几十年后的互联网自由派集体带到沟里去，让他们真的以为向丁玲和萧红学习，写几篇文章就能打倒共产党。<br>\n批判孙文本来应该只是为了证明辛的观点是错误的，但也很容易有人出于对孙文的爱戴就把评论区带偏了。的确，国民党1948年搞过选举，但孙是孙，蒋是蒋，不能说因为蒋介石搞过选举和412，孙文引共入室的罪行就一笔勾销了。","date":"2019-11-02","agreeCount":1,"discussionCount":0}