{"type":"answer","id":122553,"parentType":"question","parentId":14761,"uid":23953,"contents":"注意安全是第一位的。逞一时之快，抒一时之愤，最后受到伤害的还是自己。别看今天闹得欢，小心回国拉清单。<br>\n在这种赞歌四起的环境中，请善用沉默的权利。在蛆丛中最重要的不是和蛆辩个你死我活，而是要让蛆不要发现你，攻击你。敌强我弱，不能吃眼前亏。<br>\n如果真的想报复这个团的话，可以借机找其他的毛病，纠缠不休，最好打上所谓的爱国旗帜给自己撑腰(例如，旅游团行程安排不合理，乱收费，或者出现了别的意外，你就可以搬支国政策然后上纲上线就对了)，请善用共产主义的大旗来打败共产主义。<br>\n<br>\n我三年前的时候去的香港，那时还没有反送中革命。当时我去了香港理工，在那个时候理工大学的公告栏上就有很多关于政治的自由言论。现如今看到香港理工被警察攻占的时候真的说不出来什么滋味。<br>\n香港人给我的第一印象就是热情，有涵养。公交车，电梯，地铁，过马路，商店，到处都能看到有条不紊的排队的景象。电梯清一色站在右边，跟大陆乱哄哄的一团根本是两个世界。<br>\n导游是深圳人。那个人的素质真的不想说什么。半路强制收费，没有交钱就把我踢出旅游团了。后来不得不转成自助游，后面的几天到处都有香港的当地人帮助我。当时也感动的不得了。","date":"2020-01-06","agreeCount":1,"discussionCount":0}