{"type":"answer","id":35732,"parentType":"question","parentId":6476,"uid":8321,"contents":"我以前就公开放64纪录片，给别人看。然后给他们看韩国的几个禁片。<br>\n还有看颐和园这样的禁片。给别人发各种禁片资源。只要有人愿意看的话。<br>\n虽然没有什么大用，但别人都会有个概念，那就是共产党真坏。<br>\n只要大家脑子里有这句话，以后就能少吃很多亏。<br>\n想想那些买了p2p的可怜人，多少人就是因为信任某某大央企，信任国家，然后害死了自己。<br>\n<br>\n我觉得只要是能面对面交流的那种人，学生最好，他们一般不会说谎。<br>\n如果是社会混了很久的那种人，确实就算是见面交流，酒肉朋友，他们也不一定会说实话，也不会有什么独特的政治观点。这种人我是不会给他们传教的。<br>\n但是混熟了的那些人，我就会时不时的一起骂共产党，股市大跌要骂，工资不涨要骂，总之都要骂。<br>\n骂多了别人也就慢慢的认同了。","date":"2019-08-10","agreeCount":13,"discussionCount":4}