{"type":"article_comment","id":292579,"parentType":"article","parentId":15833,"uid":34293,"contents":"<blockquote>有一本类似的入门书籍《认识佛教》，不晓得大伙儿是否读过，里面一开始就指出：佛教是【教育】而非【宗教】...</blockquote><br>\n净土法门因为学的人多，趋于简单化了，甚至有了些基督化的色彩。首先，净土在其他宗派都有涉及，比如藏传佛教中并没有把净土单立一派。唐朝时净土法门是讲念佛三昧的，非常好的止观修法。而在观经中，也有系统的观想方法。只是越来越发展，就变成了疯狂念佛这类的东西。许多人也把净土想象为天堂一样的地方。净土法门是非常好的，但只是念佛远远不够，必须了解佛教的原理是什么。像索达吉堪布说过，不了解空性是无法往生的。可以继续念佛，然后系统学习佛教理论，具备往生四因，自然就可以去往净土的。<br>\n<br>\n往生四因是什么呢?佛经中是这样讲的，〖《极乐世界功德庄严经》云：“阿难陀，若有众生屡屡观想如来身相，〗这是往生极乐世界的第一种因;〖积累众多无边之善根，〗这是第二种因，〖发菩提心，〗这是第三种因，〖为往生彼净土而发愿、回向，〗这是第四种因。这四种因大家一定要记住。<br>\n<br>\n从文字上看，这就相当于本尊修法。所以净土法门跟变味儿没什么关系，就是人们懒了，不去深入研究，学习，修行了。总希望念念佛就可以实现一些“神奇”的事情。","date":"2020-03-12","agreeCount":1,"discussionCount":0}