{"type":"answer_discussion","id":212314,"uid":32105,"date":"2020-03-01","contents":"你说的关于男人左右脑传输快的内容是错误的。<br>\n<a href=\"https://www.ncbi.nlm.nih.gov/m/pubmed/9353793/\" rel=\"nofollow noreferrer noopener\" target=\"_blank\">https://www.ncbi.nlm.nih.gov/m/pubmed/9353793/</a><br>\nA meta-analysis of 49 studies published since 1980 reveals no significant sex difference in the size or shape of the splenium of the corpus callosum, whether or not an appropriate adjustment is made for brain size using analysis of covariance or linear regression. It is argued that a simple ratio of corpus callosum size to whole brain size is not an appropriate way to analyse the data and can create a false impression of a sex difference in the corpus callosum. The","parentType":"answer","parentId":183751}