{"type":"article_comment","id":386520,"parentType":"article","parentId":18223,"uid":418,"contents":"<a href=\"https://pincong.rocks/article/item_id-385805#\"><blockquote>論壇裏相關的帖子大概瀏覽了一遍，挺有意思的想法。結合以前那篇教導如何利用飯圈女孩來加速的帖子和現在的...</blockquote></a><br>\n<br>\n<br>\n对于你的第一个问题是，我的看法是，加速主义者不能成为大海里的一颗水滴，得成为旱地里的一颗能引来大海的水滴。你说的这三个议题，当然都是可以加速的，但是这三个议题，都已经在支国境内被加速到顶点了。就好比说战螂粉蛆到处nmsl也是一种加速，但是已经有那么多战螂粉蛆了，多你一个去反串有很大意义么？？<br>\n台湾问题在你支的舆论已经加速到顶点，剩下的不过是习敢不敢真打的问题而已。<br>\n少数民族问题维族人已经被加速到顶点情况不可能更坏了，其他少数民族诸如藏和回目前情况也不容乐观很可能未来会步维族后尘，但这些少数民族的政策我认为其实是完全不受你支民间舆论氛围影响的。但是对于那些已经完全汉化的少数民族，诸如满，挑动矛盾我倒是认为有价值的和值得赞许的。<br>\n至于香港，香港已经没救了，剩下的就是加速到底揽炒到底，以丧失独立关税地位来来成为摧毁你支经济的核弹。我相信目前香港人时日曷丧的心态比我们更强。<br>\n<br>\n对于第二个问题，加速主义确实只负责破坏不负责建设，建设需要其他的理论，但是我觉得那是加速成功之后的问题了。因为只要一谈到建设理论，左派右派解体派统一派就要吵起来了，就不可能形成统一阵线了。所以加速主义只负责破坏其实是它的优势。等加速成功了，大家再分裂开来为自己真正的理念争斗就好了。<br>\n<br>\n我始终坚持的一个理念是，情况不可能更糟糕了，我不是指生活水平上的更糟糕，而是更大的层面，文明和价值的层面。你支如今是人类史上前所未见的恶魔，即使当年的苏联，它也是和西方基本上隔离的，对西方的价值体系和威胁和动摇是有限的，哪怕闹一场瘟疫，也是很难传到美国去的。但你支不同，你支是妄图创造融合了1984和美丽新世界的反乌托邦黑暗秩序的，你支是钻了资本主义后门，动摇了西方价值体系根基的。即使你支退化成朝鲜，我也觉得一个虚弱的恶魔比一个强大的恶魔好得多。你支已经培养了成群的恶魔，情况再差也差不到哪去了。<br>\n<br>\n而另一方面来说，只有秩序的失控，控制的失控，像清末这样，你才有传播思想的空间，这种空间，现在是完全不存在的。你支目前已经完全没有教化的空间了，至少加速成功之后，才有以文明来教化的可能性存在。在加速主义毁灭一切后，至少会产生新的可能性，而现在，你支不存在任何可能性。","date":"2020-05-22","agreeCount":2,"discussionCount":0}