{"type":"article_comment","id":22042,"parentType":"article","parentId":2340,"uid":6345,"contents":"一、中国对于外国互联网公司在中国提供服务有明确的监管要求。比如必须在国内设置公司运营，所有用户数据必须保存在国内，当然还有配合审查。同样是搜索引擎，Google走了，但是微软的必应就可以留下来。<br>\n我不评论这些监管要求的好坏，但是企业不接受这些监管要求是他们自己的选择。<br>\n而美国呢？华为自己倒是很希望美国提出监管要求，但是没有的。我从来没听美国说过，你华为要做到1、2、3我就能让你卖东西。而是不给任何机会的封杀。<br>\n<br>\n- 符合監管要求的情報機構難道不是情報機構??  根據中國《國家情報法》，為國家從事情報活動是一種義務。法律已經寫明,  華為作為一間在中國如此大型的公司, 你相信中國政府沒有利用華為作情報活動??? 中國政府權力一直無人可以監管制衡下, 中國政府是世上權力最大的政府之一, 內部沒有一絲監管制衡, 對國內的控制遠比民主政體高. 根本所有有關個人私隱既中國企業都不可信. 中國企業不合作難道可以告中國政府???<br>\n<br>\nFacebook 同美國政府可以為保障用戶私隱告上聯邦法院, 你相信在中國可以發生?? 不要提美國稜鏡計畫, 我沒有說美國政府是正義使者, 每一個政府都會極力擴展自己的權力. 這是權力的天性 關鍵是有沒有制衡的力量, 你信不信他有制衡力量的存在.<br>\n美國華盛頓郵報能夠公開稜鏡計畫正正說明美國有良好運作的第三權.<br>\n<br>\n二、中国本土不能访问Facebook、Google这些服务。但是中国从来没有禁止国内的公司和Facebook、Google他们往来。相反，很多中国公司都是他们的广告大客户，Google和华为甚至在安卓上有着深度的合作。<br>\n<br>\n  -  不要把中國沒有禁止國內的公司和Facebook、Google他們往來說成中國政府大發慈悲. 正正是中國明知自己建立了一個世界上最大的內聯網, 中國公司如果要國際化發展, 難道在內聯網向中國人宣傳???<br>\n<br>\n而美国呢？不止禁止国内公司和华为往来，甚至还要求美国以外的公司也停止和华为的往来，让各个公司都苦不堪言。<br>\n你美国觉得华为的网络设备和手机不安全，你不买可以。但是你凭什么连你的盟友在向你要华为不安全的证据你都给不出的情况下，就去影响上亿的华为手机用户和那些数十个甚至上百个信赖华为的国家呢？<br>\n<br>\n对不起，这种事情中国没有做过，也做不到。 <br>\n<br>\n-  這種事情是中國做不到。所以沒有做過。你覺得中國有能力會不做嗎? 你真的覺得中國是這麼正氣正義嗎??<br>\n美國要封殺華為當然要盟友配合, 不然單方面封殺, 然後華為經其他歐洲公司繼續購買美國貨. 這封殺有意義嗎?","date":"2019-07-15","agreeCount":4,"discussionCount":0}