{"type":"answer","id":118090,"parentType":"question","parentId":1115,"uid":25711,"contents":"马克思发现的一些事实，剩余价值，剥削，仍然在中国普遍上演。从加班猝死，996到251，这些资本家仍然贪婪，并且在一个低保障低福利、谋求发展而牺牲个体的国家里是更加常见的。<br>\n<br>\n马克思的科学能力不算高。曾经有中国数学教材指出马克思热衷数学题，还有小册子记录各种题。其实像他那样的哲学家，怎么可能有多高的科学水平。他喜欢这样的表述“直线也可能是曲线！高等数学处处是矛盾，高等数学充满了矛盾！矛盾转化，矛盾统一……”云云。全然不是研究科学的料。于是，选择跨行讲综述，踏上自创哲学之路……<br>\n<br>\n马克思使许多人相信底层人民需要革命来获得更好的生活。如今一个成熟的民主制度里，工人不必流血而仅依靠选票就能够表达自己的诉求。还有许多类似的鼓动性的话，都需要重新审视。<br>\n<br>\n其他的更复杂的我不懂。另外，将马克思主义中国化很像是洪秀全说自己是上帝的二儿子。借个外壳，直接说令人摸不找头脑的新话了。","date":"2019-12-31","agreeCount":4,"discussionCount":0}