{"type":"answer","id":58918,"parentType":"question","parentId":9391,"uid":7461,"contents":"後續<br>\n<a href=\"https://news.mingpao.com/ins/%e6%b8%af%e8%81%9e/article/untrusted fake 2049bbs6%b8%af%e8%81%9e/article/20191008/s00001/1570466125177/%e3%80%90%e7%a6%81%e8%92%99%e9%9d%a2%e6%b3%95%e3%80%91%e7%9a%84%e5%a3%ab%e6%b7%b1%e6%b0%b4%e5%9f%97%e6%92%9e%e5%82%b7%e4%ba%ba-%e8%ad%a6%e6%8b%98%e4%b8%80%e9%9d%92%e5%b9%b4%e6%b6%89%e6%9a%b4%e5%8b%95-%e7%9a%84%e5%a3%ab%e5%8f%b8%e6%a9%9f%e6%9c%aa%e8%a2%ab%e6%8d%95</a>\t\t</div>\n\t\t<!-- end 回答 -->\n\t</div>\n\t<div class=\" mod-footer\"=\"\">\n\n</a><div class=\"meta clearfix\"><a href=\"https://news.mingpao.com/ins/%e6%b8%af%e8%81%9e/article/untrusted fake 2049bbs6%b8%af%e8%81%9e/article/20191008/s00001/1570466125177/%e3%80%90%e7%a6%81%e8%92%99%e9%9d%a2%e6%b3%95%e3%80%91%e7%9a%84%e5%a3%ab%e6%b7%b1%e6%b0%b4%e5%9f%97%e6%92%9e%e5%82%b7%e4%ba%ba-%e8%ad%a6%e6%8b%98%e4%b8%80%e9%9d%92%e5%b9%b4%e6%b6%89%e6%9a%b4%e5%8b%95-%e7%9a%84%e5%a3%ab%e5%8f%b8%e6%a9%9f%e6%9c%aa%e8%a2%ab%e6%8d%95</a>\t\t</div>\n\t\t<!-- end 回答 -->\n\t</div>\n\t<div class=\" mod-footer\"=\"\">\n<span class=\"aw-small-text pull-right\">2019-10-08</span>\n\n<span class=\"operate aw-vote-ui\">\n</span></a><a href=\"javascript:;\" class=\"agree disabled\">\n<i class=\"icon icon-agree\"></i> <b class=\"count\">0</b>\n</a>\n\n\n<span class=\"operate\">\n<a href=\"javascript:;\" onclick=\"toggle_disscusion($(this));\" class=\"aw-add-comment\" data-id=\"58918\" data-type=\"answer\" data-comment-count=\"0\"><i class=\"icon icon-comment\"></i> 0</a>\n</span>\n\n<div class=\"more-operate\">\n<a href=\"/vote/log/item_type-answer__item_id-58918\" class=\"aw-small-text\" rel=\"nofollow\" target=\"_blank\"><i class=\"icon icon-users\"></i></a>\n</div>\n\n</div>\n\n\n<div class=\"aw-comment-box\" style=\"display:none\">\n<div class=\"aw-comment-list\"></div>\n\n<a class=\"aw-load-more-content\">\n<span>更多</span>\n</a>\n\n<form action=\"/question/ajax/save_answer_discussion/answer_id-58918\" method=\"post\" onsubmit=\"return false\">\n<div class=\"aw-comment-box-main\">\n<textarea class=\"aw-comment-txt autosize form-control\" rows=\"2\" name=\"message\" placeholder=\"讨论一下...\"></textarea>\n<div class=\"aw-comment-box-btn\">\n<span class=\"pull-right\">\n<a href=\"javascript:;\" class=\"btn btn-mini btn-success\" onclick=\"submit_disscusion($(this));\">讨论</a>\n</span>\n</div>\n</div>\n</form>\n</div>","date":"2019-10-08","agreeCount":0,"discussionCount":0}