{"type":"question","id":15254,"title":"你更希望改革还是革命（激进的还是渐进的变革）？","uid":24523,"topics":[2933,910,419],"contents":"我自认为是政治和文化中道偏右的，我本希望中国能够没有留血缓慢变迁走向普世和世界潮流。<br>\n奈何中共逆潮流而行，使我逐渐产生了一种不破不立，需要推翻重来的想法了。<br>\n<br>\n我现在每每看到包子军演，学习墙国，坏球新闻，胡🐶叼盘，竟然心中逐渐快乐了起来。<br>\n也许我尝到了围观加速主义的快感了。<br>\n<br>\n我最关心的是国民 是民众 是普通人。最近仔细一想，我也许根本不是绝对反感激进变革，我仅仅是反感留血、以及对无辜大众造成伤害罢了。<br>\n纵观历史，并不是所有激进变革都等同于平民的巨大牺牲嘛！东欧也是瞬间崩溃了那些骨子里邪恶的政权，却大多是和平的。<br>\n更何况，不变革只会让更多的普通人流更多的血啊（远到土改反右，近到六四屠杀，今到香港新疆）<br>\n<br>\n各位是支持加速加速再加速导向崩溃呢，还是希望缓慢的改革呢？","date":"2020-01-13","agreeCount":4,"discussionCount":3}