{"type":"question","id":19867,"title":"刚看了土耳其总统erdogan的采访，他好像对武汉病毒毫不担心？","uid":29992,"topics":[5950,5419,488],"contents":"我在美国上过15堂课的入门级土耳其语课程（&nbsp; 我也学过一个月的西班牙语，但只停留在认识西语的27个字母和5个双辅音的层面），加上Google翻译器的帮助，勉强能看懂简单的土耳其语新闻。<br>\n<br>\n<br>\n土耳其总统erdogan，两天前接受Anadolu Ajansı（&nbsp;Anadolu Agency)，土耳其国营通讯社的采访，他觉得武汉病毒的疫情严峻性并没有那么可怕，死亡率很低，可防可控，无需刻意制造恐慌情绪。<br>\n<br>\n<br>\n大致总结了几点，他的表态内容。<br>\n<br>\n第一：土耳其的所有公立和私立医院，诊所等医疗机构，加起来有25万病床存量，必要时还可以征用军队医院的大量床位。<br>\n<br>\n<br>\n第二：土耳其有数千万个口罩和防护服的国家战略储备，每天最高可以生产800万口罩。<br>\n<br>\n<br>\n第三：土耳其有世界上一流的医疗设备，公共传染病专家和足够的医生，公共卫生体系经验丰富，我们的药品是充足的，并且经受住了2009年甲型流感的考验。既不缺医，也不少药。<br>\n<br>\n<br>\n第四：武汉病毒的死亡率很低，不超过1%，致死率相当于一个严重的流感，死亡病例主要是患有基础病的老年人（&nbsp;支那是例外，在<mark>支那</mark>死亡率是3.7%，在武汉死亡率是5%）。<br>\n<br>\n<br>\n第五：土耳其目前还没有确诊病例，政府已经采取了所有必要的防范措施来应对疫情，包括中断和中国伊朗的航班，关闭和伊朗之间的陆地边境，对所有来自中国旅客实行14天的强制隔离。<br>\n<br>\n<br>\n<br>\n<br>\n总而言之，死亡率低于1%，严重性很低的病毒，重症患者很少，轻症患者占大多数，有一定传染性，我们已经做了所有必要的防范措施，可防可控，不需要神经紧绷，过度紧张。","date":"2020-03-01","agreeCount":1,"discussionCount":1}