{"type":"question","id":22830,"title":"你如何看待人体？","uid":25982,"topics":[8152],"contents":"# 你如何看待人体？<br>\n<br>\n当我看到中国人最爱的各种思想，我最后想问：你如何看待人体？<br>\n<br>\n中国人那么聪明，最后还不是消灭人体吗？<br>\n<br>\n有那么多思想、理论，然后有历史，社会科学，爱国恨国，最后还不是要杀人吗？<br>\n<br>\n然后又高明的告诉我：你先要有不杀人的思想然后才能不杀人。<br>\n<br>\n算了，你直接告诉我你如何看待人体。<br>\n<br>\n我们不要进入神学讨论中，<br>\n我能不能说这是神的法则：<br>\n人体是神定的边界。<br>\n<br>\n我们只低头看一条法则而不去试图抬头张望神的更大的领域。<br>\n<br>\n中国人是不是一直在践踏神定的法则：侵害人体？<br>\n<br>\n当人类有了语言，<br>\n中国人就开始禁言，<br>\n也是对人体扩展的边界进一步的践踏吧？<br>\n<br>\n以伤害人体达到禁言的目的，<br>\n为什么让人感觉这是一种无法进化的生物？<br>\n<br>\n所以我的问题只是你如何看待人体？<br>\n<br>\n如果一个男人狂野的想要抱紧一个女人，<br>\n或者一个女人热切的想要一个男人来抱住自己，<br>\n他们的身体会靠近，<br>\n人体边界会贴在一起，<br>\n最后我知道人类侵犯人体边界的欲望无法遏制，<br>\n并且也不全是恶意，<br>\n但是，我还是问这个问题：<br>\n你如何看待：人体。","date":"2020-04-05","agreeCount":2,"discussionCount":4}