{"type":"question","id":29900,"title":"那些在大陆被请喝茶的具体原因是什么？","uid":31931,"topics":[733,502,613,3769,112],"contents":"现有问题&nbsp;<a href=\"https://pincong.rocks/question/23881\" rel=\"nofollow noreferrer noopener\" target=\"_blank\">https://pincong.rocks/question/23881</a><br>\n和&nbsp;<a href=\"https://pincong.rocks/question/7226\" rel=\"nofollow noreferrer noopener\" target=\"_blank\">https://pincong.rocks/question/7226</a>，但是最根本的原因还是在于本人和海外帐号的关联是怎样被大陆审查找到的。<br>\n是因为使用了大陆的手机号？还是使用了大陆的邮箱？还是海外的邮箱和手机号等这些相关连的东西和本人有联系，能通过社会工程学的方式，也就是链状关系找到？还是因为账户名、内容上泄漏了本人的信息？<br>\n<br>\n我觉得<b>不应该仅仅用“推特危险，别上推特”继续让民众进行自我审查</b>，而是应该把实际的注意事项、这个平台含有风险的地方详细列出来，鼓励让更多的人得到本来就应得的话语空间。<br>\n<br>\n而且<b>不是说用“请喝茶不是个大事，顶多批评批评”这种方式来鼓励，（</b>大多数中国人其实挺难放地这么开）<b>而是说怎么能从技术上从根源消除“被请喝茶”，让你在墙外的联系和真人之间完全不可达，</b>根源上消除大部分翻墙者的恐惧心里。<br>\n<br>\n<b>我希望本问题的回答，大家更侧重于，“我被请喝茶，到底是因为什么原因才导致他们跟着我的推特号找到我本人的？”。</b>即使是推特内部有渗透，后门敞开，那么我觉得我用个小VPS混淆一下代理，注册个protonmail，再在退特上大骂习近平的极权统治，谁找的到我啊？<br>\n<br>\n目前本人依旧无法无天，其实你们都可以这样，我觉得只是有些细节没注意。","date":"2020-08-16","agreeCount":2,"discussionCount":0}