{"type":"question","id":6711,"title":"日本侵略者制造的万人坑和中国制造的山西煤矿矿难，哪个更恶劣","uid":9297,"topics":[1261],"contents":"我们都知道，当初日本侵华，制造了几个大万人坑。<br>\n<br>\n什么是万人坑，就是挖煤死亡的矿工，尸体堆在尸坑里<br>\n<br>\n2000年到2010年，正是煤价高涨的时候。我记得新闻上每周都报道山西矿难，死的人从来不低于10个。（个位数不值得上新闻，而且瞒报死亡人数也都不谈了）<br>\n<br>\n按每周死10个矿工，一年死520人，10年5200人。这可只是山西一个省死的人。<br>\n<br>\n再加上其他省，多少个万人坑了？<br>\n<br>\n日本鬼子制造万人坑，因为他们是侵略者。外族人。而且1935到1945年，那是将近一个世纪以前，挖矿科技不发达。<br>\n<br>\n中国制造的矿难，可是科技发达的二十一世纪。<br>\n<br>\n所以我说，虽然北上广和山西都是中国领土，但实际上，山西就是北上广和东南沿海的殖民地。<br>\n<br>\n除了山西，东北、内蒙、新疆都是被中国奴役压迫掠夺的殖民地啊","date":"2019-08-14","agreeCount":0,"discussionCount":0}