{"type":"answer","id":187511,"parentType":"question","parentId":19827,"uid":14330,"contents":"我没什么知识素养，只是说说自己的想法……<br>\n<br>\n人类是群居动物，群体是必定有头领才有凝聚力的。一群老虎需要有虎王，一群狼也需要狼王，鹿自然也有头领。即便再怎么强调个人主义，人群还是需要领袖，需要精神上的信标。香港示威是无大台，但他们也是有精神信标的，只不过不是某个人而已。是光复香港旗、是梦中的民主香港，这些东西其实也是非人格化的领袖——旗帜向哪儿，人群就会走向哪儿，这不正是领袖吗？<br>\n<br>\n对于有神论者，他们最终的精神信标是神。神存在吗？它可以不存在，也可以存在；可以存在在天上，可以存在在心中。神是不可捉摸、没有实体的，神可以解决【一切问题】。无论是多么伟大的存在，只要是凡间的存在，都不可能大过神。所以如果凡间的存在背叛了神的旨意，人就可以以神之名去反对他。<br>\n最重要的一点就是【神无实体】，所以神【有无穷的可塑性】。只要将自己的想法用神为媒介传达出去，人民就会在潜移默化中接受。任何政权、任何组织都无法磨灭，因为人不能踩在神的头上。<br>\n当然，神的无穷可塑性给了邪教害人的空间，好比撒旦也是无穷可塑的；但是也有好的一面。文艺复兴时期的文艺作品，大量集中在宗教题材上。无数艺术家、作家诠释着神话故事、天国景象，融入了他们自己的意志。他们的作品，成为了开启民智的钥匙。<br>\n只有无实体的神，才有可能作为一大群人的精神信标，带领人们向善、向美。一个伟人、一个全是伟人的组织是不够的，因为人类是不可能做到【绝对正确】的，世上可以绝对正确的只有神。人类永远不能成为神，但人类却需要神。<br>\n<br>\n对于无神论者，他们不信仰神，也必定会有信仰。因为要想把人凝聚在一起，不可能没有领袖。但不信神又信什么呢？比如信共产党，信共产主义，当然是可以的。但是共产主义是人造的理论，人造的理论就不可能绝对正确，所以共产主义者一定有【得不到答案】的时刻。共产党也是有实体的，所以共产党也【不能解决一切问题】。所以一个把共产主义、共产党放在至高地位的人，在遇到无法解决的问题时就会陷入矛盾。他们的问题其实就是不信神，不信存在一个绝对正确、能解决一切问题的神。人如果信神，就会明白世间一切都是有缺陷的，共产主义、共产党也一样，于是自然就能从共产信仰里走出来。<br>\n<br>\n信神，在于信一个绝对的存在。人永远也无法领悟神的真理，因为人永远也做不到绝对正确。但是信神，就不会误把人造的理论当作神的真理、当作绝对正确的真理，这对于解放人的思想是很重要的。当然，有被恶用的可能性，会有人编造邪恶的理念，假借神的名义向人民传播。但是不能否定其正面意义。<br>\n<br>\n另外，科学和宗教没有关系。一个理论中无穷发达的科学，能解释世间一切问题的科学，本身已经达到了“神域”，不是只能活在三次元世界的人能企及的。不存在“信仰科学”，或者说，信仰科学的行为本身，也是在信仰一个绝对正确、能解决一切问题的神。","date":"2020-03-02","agreeCount":19,"discussionCount":4}