{"type":"answer","id":302342,"parentType":"question","parentId":28274,"uid":7113,"contents":"以為抽硬盤是比喻或俚語暗語，沒想到是真的抽硬盤<br>\n<br>\n<a href=\"https://hk.appledaily.com/china/20200708/4DRP4NCQPQ2ERZ6ZE3ATXSDQVE/\" rel=\"nofollow noreferrer noopener\" target=\"_blank\">https://hk.appledaily.com/china/20200708/4DRP4NCQPQ2ERZ6ZE3ATXSDQVE/</a><br>\n【驚人舉動】李克強巡數據中心隨手抽出硬碟 網民大驚：個人資料任意攞走 ｜ 即時 ｜ 兩岸 ｜ 20200708<br>\n<br>\n很多人都搞錯了，習李未必存在權鬥，僅僅是禁止評論習的醜聞，李尺度寬鬆些，造成錯覺五毛在黑李，其實是因為李地位不如習，沒必要太護主","date":"2020-07-10","agreeCount":3,"discussionCount":1}