{"type":"article_comment","id":88635,"parentType":"article","parentId":6933,"uid":12438,"contents":"你需要赞么？还是打算换号/退葱？我觉得你不像五毛，希望能保护你发言权。<br>\n你说的第一点中国大陆没有品葱描述的那么遭，这个我部分赞同，过去30年确实是中国迅速发展的时代，今天中国抛开政治参与和自由程度在全世界而言生活水平也是中上的。<br>\n但是我觉得一个国家在上升期只要不是糟糕透顶的政党去执政社会总体都是上升发展的，比如工业革命时代的英法德，这种增长是由于客观因素推动的。当然政府不能阻断这种发展趋势，政府对发展的阻力大小会影响到经济增长速度和时间长度。<br>\n近两年可以看到中共政府对经济发展起到的负面影响越来越大，比如在过去夹缝中成长的文娱产业最近就被宣传和维稳彻底牺牲了。其实前些年社会上有好多微创新，都是在整个行业还没形成雏形之前就被政府叫停了，不然发展到现在可能已经在小行业里做到了世界领先/垄断。因为政府需求产生的行业风口可能也就是监控系统这一个。<br>\n你这个评论里面也有党国不分的感觉，第一句你隐含的想法是把十来亿公民在有限自由下取得的经济发展成果算成了共产党的成果。党国不分是中国大陆成长的人普遍存在的问题，不信你唱几句歌唱祖国，是不是内心突然觉得共产党带领中国复兴共产党真伟大？这首歌被传唱的只有第一段，这一段里面没有一处提到了共产党。所以被洗脑到党国不分是深存在潜意识里的，连我这样反了十几年共的都没能做到彻底清除。","date":"2019-10-24","agreeCount":2,"discussionCount":0}