{"type":"answer","id":84241,"parentType":"question","parentId":11619,"uid":12438,"contents":"我来说个你们看了不开心的，成立独立调查委员会追究警队滥权这个诉求现阶段其实可以拿掉不提。<br>\n香港人权与民主法案已经通过，中共军队和武警轻易不会明着入场，只要中共不出兵敌人唯一的主力就是香港警察。五大诉求里警察最怕的是独立调查，这也是他们镇压这么卖力的一大原因，我不觉得他们很关心其他几项。只要能暂时忍耐一下向警察妥协，分化瓦解他们，这场运动就很容易成功了。<br>\n可能这么做会丢失一些证据放过一些黑警，让人感情上难以接受，但最关键的是民主运动能否成功，毕竟诉求再好不能实现又有什么用。只要港府可以民主选举了到时想限制警队权力还不容易？<br>\n<br>\n警察是港府和中共中央目前唯一可以依靠的力量，他们摆明了是不可能自毁长城的。<br>\n 这里推演一下可能性。<br>\n第一种是警察卖力镇压，运动被警察压制下去，什么都没有改变，这是中共最满意的结局。<br>\n第二种是警察卖力镇压，但是最终还是民众成功了。这时中共有a答应五大诉求和b放弃所有涉港经济利益派兵镇压两个选项。<br>\n第三种是五大诉求变四大诉求，对警察拉拢一批分化一批，但运动还是不成功。除了让大家知道警察不是铁板一块的以外什么都没有改变，这是中共第二满意的结局。<br>\n第四种是五大诉求变四大诉求，对警察拉拢一批分化一批，运动成功了。这时中共有答应a四大诉求和b放弃所有涉港经济利益派兵镇压两个选项。<br>\n对我们来说最好的自然是可能性2a中共答应五大诉求，但是运动目前已经僵持太久，成功几率有多少很难说。我认为应该去追逐4a结局，成功率一下就大增，而且除了感情上不容易接受成果其实并没有减少。","date":"2019-11-21","agreeCount":2,"discussionCount":16}