{"type":"article_comment","id":227956,"parentType":"article","parentId":13711,"uid":16955,"contents":"<blockquote>首先呢，其實好像『漢語也是中華文化，你不喜歡的話就別用了，也別來蔥這種帶有中華文化的垃圾論壇了。』這...</blockquote><br>\n反之，我觉得你全盘否定某种文化的行为，本来就跟那些粉红粪青五毛完完全全相同，只要看看他们是怎么全盘否定西方的某些文化就知道了。哦不，全盘否定中华传统文化的当然不是粉红粪青五毛，不正是当年腊肉太祖带着的红卫兵红小将么。这里葱油们的眼睛是雪亮的，能看出是不是有赤共的人来这里挑拨离间，来分化好不容易聚在一起的反贼们。<br>\n<br>\n我从没说过中华文化全部都是好的。中华文化包容万象，有精华也有糟粕。由于历史悠久，这两方面都占有很大的比重。而这点，像你这种人是永远不会懂的。不会用西方的trial-and-error的方式去看待事物，而是用第三共产国际的主义、思想、教旨去两极化地判断事物的好坏，不正是赤共的现在的典型做法么？对了，现在赤共都会为了金钱去做些妥协了，不知道接受了腊肉太祖的思维方式的你会不会哦？<br>\n<br>\n我曾经在ABC好友家里长居过，跟一些基本没接触中华文化的二代三代ABC有很深的交情(实际上不少是第一代是台湾来的)，也跟从小上中文学校学中文的ABC相聊盛欢，我不觉得他们之间有什么特别的优劣，据我观察，之后他们的人生发展也是。像你这种没有机会去真正接触所谓的“竹昇仔”的人可能是无法体会的吧。<br>\n<br>\n我不知道你如果是为自己发言的话，全盘否定某种文化的意义何在。当然，我们美国政府庆祝农历新年这种行为估计也是脑袋进水，被某种“低劣”的文化给负面地影响了吧：http://www.asian.gop/events/2018-white-house-lunar-new-year-celebration。<br>\n<br>\nIn addition, if you are able to understand English, feel free to have a conversation with me. You should abandon using Chinese, either simplified or traditional, as your way of communication, if you entirely deny the Chinese culture. Chinese as a language is part of the Chinese culture, which is the fact that you have no way to deny.<br>\n<br>\n我看过了你的简介，我不知道什么样的经历会让你产生这样的想法。如果你愿意分享原因，而不是情绪化地表达否定与负面，我想你的论点会更有说服力。<br>\n<br>\n我也没打算说服你，有可能我打字只是浪费自己的时间，因为我是为自己的想法说话，而你可能是拿了钱在这里为某台机器发言而已。","date":"2020-02-05","agreeCount":1,"discussionCount":0}