{"type":"answer","id":7511,"parentType":"question","parentId":1615,"uid":1940,"contents":"声明：<b>没有任何一个民族有所谓的劣根性</b>。再说一遍，<b>没有任何一个民族有所谓的劣根性。最后说一遍：</b><b>[b]没有任何一个民族有所谓的劣根性</b>[/b]。<br>\n<br>\n只有这个民族<b>是否被改造的十分彻底</b>。<br>\n<br>\n<b>法律的基本准则是建立在公认的行为准则的确立，且被多数人所接受的行为共识。换成人话就是【即使法律保护不了你，至少让你自己保护自己】</b><br>\n然而，这个地球上就是有那么一个奇怪国家的法律：<br>\n<br>\n<b>它保护不了你，也不允许你自己保护自己。只保护那些制定这些法律的人。</b><br>\n为了挤进那些制定<b>这些法律的人里希望成为被保护的对象。</b><br>\n而完完全全的忽略了这个<b>法律存在的合法性</b><br>\n这样的民族，<b>我们也只能为他们感到悲哀了。</b>","date":"2019-01-25","agreeCount":1,"discussionCount":1}