{"type":"answer","id":76850,"parentType":"question","parentId":10958,"uid":16154,"contents":"家里人很早就教我识字 小时候因为身体不好不怎么出去玩 就喜欢在家看书 什么都看 后来翻到我爸买的一些书本刊物 看了很多讽刺官场腐败官员包养情妇之类的小说文章 从小就有一个印象就是官员都是大腹便便二奶多爱受贿的形象 一直很反感升国旗强制戴红领巾听少先队队长讲话之类的形式主义（洗脑） 初中的时候了解了六四 同学在hk买了图册带来班上看 受到了冲击（初中保守估计半个班反贼 还有一半不关心政治 后来基本上全出国了 不过有趣的是这两年tg宣传能力大有长进 许多以前的资深反贼同学变成离岸爱国自干五了） 和我爸去hk买了很多禁书 一点点啃完（近代史到现在还没看完） 当时是全班第一本来班主任让我第一批入团然后我一直不肯 到现在也没入 然后后来住校遇到的舍友几乎全是讨厌tg或者不关心政治的 高中整个学校都非常有民主意识 办lgbt杂志和在校电视台栏目讨论、食堂吃出虫子搞民主投票要学校调查 后来驱逐低端人口事件大家都很愤怒发朋友圈各种讽刺骂tg（我也发了被我爸妈让删了） 一直到现在我肉翻了 在国内最关心最爱点评时事的还是那些女同学 男生反而自干五或者岁静只关心游戏动漫的多","date":"2019-11-13","agreeCount":20,"discussionCount":5}