{"type":"answer","id":16939,"parentType":"question","parentId":3048,"uid":3700,"contents":"简单的说，就是大陆的小朋友不关心自己的国家，对自己的国家一无所知，连基督教在中国的发展趋势都不知道，只知道共产党洗脑的东西而已<br>\n<br>\n关于中国基督徒人数，官方已经公布过几个数字。1982年中共中央19号文件说，1949年时有基督徒（仅算基督新教）70万，文件发布时已经增长到300万，1997年首个宗教白皮书承认已经有1000万，2009年新华社在庆祝建国60周年的文章中说已达1600万，2018年第二个宗教白皮书说已经是3800万。根据这组数字简单算一下，虽然从1966到1979禁教13年，文革后比建政初基督徒人数却增长了4.3倍，超过人口增长速度。从1982年到1997年15年净增长7百万，平均每年增长不到50万。从1997年到2009年，12年净增长600万，平均每年增长50万。从2009年到2018年，9年净增长2200万，平均每年增长244万多。也就是说，根据最权威的官方公布数字，自从改革开放以来，基督徒人数增长显然越来越快，而不是如官学所说近来已经放缓。<br>\n<br>\n&nbsp;在共产党的统治下，中国基督徒从70万变成几千万，如果这不是大规模基督教化，我也没有什么可说的。这些东西都是大陆人自己的资料，外面估计的基督徒人数更多，甚至有到八千万的惊人数目，这些事情，你们一无所知<br>\n<br>\n共产党才是世界上最好的传教士，无神论者对基督徒的生命和人数增长最有贡献，这不能说不是一种讽刺","date":"2019-04-12","agreeCount":0,"discussionCount":2}