{"type":"article_comment","id":302115,"parentType":"article","parentId":16361,"uid":15768,"contents":"加速！加速！加速！加速！加速！加速！<br>\n<br>\n前面是千里高山！加速！加速！加速！<br>\n<br>\n前面是万丈悬崖！加速！加速！加速！<br>\n<br>\n2020全面小康！加速加速加速！<br>\n<br>\n中华民族的伟大复兴！加速加速加速加速加速加速加速加速加速加速加速加速加速加速加速加速加速加速加速加速加速加速加速加速加速加速加速加速加速加速加速加速加速加速加速加速加速加速加速加速加速加速加速加速加速加速加速加速加速加速加速加速加速加速加速加速加速加速加速加速加速加速加速加速加速加速加速加速加速加速加速加速加速加速加速加速加速加速加速加速加速加速加速加速加速加速加速加速加速加速加速加速加速加速加速加速加速加速加速加速加速加速加速加速加速加速加速加速加速加速加速加速加速加速加速加速加速加速加速加速加速加速加速加速加速加速加速加速加速加速加速加速加速加速加速！","date":"2020-03-18","agreeCount":10,"discussionCount":0}