{"type":"answer","id":110198,"parentType":"question","parentId":13672,"uid":8841,"contents":"&nbsp;我觉得比起读取你的手机信息来说，APP强行下载市场更让他们关注。<br>\n<br>\n因为很多软件都有捆绑，不，说很多已经太善良了。百分之九十九的软件都捆绑，这就代表着下载一个不仅有一个下载流量，还有了其他软件的下载。<br>\n<br>\n从市场方面看，国内大部分使用的营销战略还是市场份额，很多公司寻求广告合作以及融资的时候，拿出的数据都是“使用用户数量”，这个和下载有很直接的关系。<br>\n<br>\n其次，从客户消费上看，国内大部分人都没有消费意识的。换句话说，能不交钱就不交钱，这种情况下，APP只能是信息提供方，但运营成本也许有的呀，如果你们光使用平台却榨不出油水，这个APP相当于赔钱运营呢啊。因此，为了捆绑广告和其他的一些软件，就导致了强迫用户下载的手段，你不下载就不让你使用，不让你看信息。<br>\n<br>\n其实这种环境不仅有公司的责任，还有广大用户的责任。","date":"2019-12-21","agreeCount":1,"discussionCount":0}