{"type":"article_comment","id":348854,"parentType":"article","parentId":17835,"uid":45307,"contents":"[url=https://pincong.rocks/article/item_id-348390#][/url][url=https://pincong.rocks/article/item_id-348390#][/url]<blockquote><a href=\"https://pincong.rocks/article/item_id-348390#\">粉紅無見識就算了，連使館人員都坐井觀天，出這類聲明貽笑大方令人尷尬，出醜於國際。 </a></blockquote><br>\n[url=https://pincong.rocks/article/item_id-348390#][/url][url=https://pincong.rocks/article/item_id-348390#][/url][url=https://pincong.rocks/article/item_id-348390#][/url]<br>\n他還以為推特是他微博呢。不過幣竟有照例監和華蠢營在他上面，有這種蠢話也不算太出人意表。<b>應該說發表了甚麼正常的外交辭令才是大新聞。</b><br>\n而且他好意思說啥中泰一家親，不是剛在湄公河上游修水壩要斷人家活路嗎？真不要臉。<br>\n[url=https://pincong.rocks/article/item_id-348390#][/url][url=https://pincong.rocks/article/item_id-348390#][/url]","date":"2020-04-17","agreeCount":3,"discussionCount":0}