{"type":"answer","id":247107,"parentType":"question","parentId":23997,"uid":8240,"contents":"个人说说我在澳洲的感受吧。为什么澳洲比很多其他西方国家都反中(并不仅仅是反共)？<br>\n<br>\n1.我觉得澳洲跟台湾的处境是很相似的，都是经济依赖中国，但是政治靠拢西方。首先澳洲的地缘位置在所有西方国家算是离中国最近的，这种近就带来了很多问题，例如澳洲经济非常依赖中国，澳洲出口很大一部分就是矿业，但是了解中共的都知道，中共可以拿任何东西当筹码，所以澳洲就出现了澳洲被中共掐着经济命脉但是却拼命跟中共对着干的奇观。而这两年澳洲频频爆出有政客受中共支持的财团资助的就是这个原因，中共统战拿这些筹码来影响他国内政不是一两天了。<br>\n<br>\n2.中共和中国人有钱，而民主国家基本上是买卖自由的，这就导致澳洲的很多原本国有的产业被中国买走而变为外资，外资在有问题的时候往往跑到是最快的。再说中国人有钱，中国人来澳洲拖家带口满地开花，炒高房价，当然让很多买不起房的本地人不爽了。<br>\n<br>\n3.近些年来的大陆中国人在澳洲喜欢搞小团体，墨尔本悉尼布里斯班都有华人区，很多新移民不像老移民会努力同化融入社会而是自己跟自己玩，这就造成了国中之国，享受者澳洲的福利却给中共背书。另外很多大陆人喜欢搞代购，药店超市代购奶粉药品的一抓一大把，当真令人反感<br>\n<br>\n4.澳洲媒体确实喜欢报中国的黑料，但是谁让你自己黑点太多了<br>\n<br>\n总之我个人算融入的比较好的，我从来没把自己当外人，所以从来也没人歧视我<br>\n<br>\n4.","date":"2020-04-23","agreeCount":5,"discussionCount":0}